{
  "updated_at": "2026-05-06T20:54:26+00:00",
  "source": "https://open-meteo.com/",
  "cities": [
    {
      "name": "Hanoi",
      "name_ja": "ハノイ",
      "lat": 21.0285,
      "lon": 105.8542,
      "temperature": 24.6,
      "apparent_temperature": 29.5,
      "humidity": 97,
      "wind_speed": 9.2,
      "weather_code": 1,
      "is_day": 0,
      "local_time": "2026-05-07T03:45"
    },
    {
      "name": "Ho Chi Minh City",
      "name_ja": "ホーチミン",
      "lat": 10.8231,
      "lon": 106.6297,
      "temperature": 27.2,
      "apparent_temperature": 32.6,
      "humidity": 87,
      "wind_speed": 8.7,
      "weather_code": 0,
      "is_day": 0,
      "local_time": "2026-05-07T03:45"
    },
    {
      "name": "Da Nang",
      "name_ja": "ダナン",
      "lat": 16.0544,
      "lon": 108.2022,
      "temperature": 26.1,
      "apparent_temperature": 31.5,
      "humidity": 88,
      "wind_speed": 4.9,
      "weather_code": 0,
      "is_day": 0,
      "local_time": "2026-05-07T03:45"
    },
    {
      "name": "Hue",
      "name_ja": "フエ",
      "lat": 16.4637,
      "lon": 107.5909,
      "temperature": 24.2,
      "apparent_temperature": 29.5,
      "humidity": 97,
      "wind_speed": 4.3,
      "weather_code": 0,
      "is_day": 0,
      "local_time": "2026-05-07T03:45"
    },
    {
      "name": "Hai Phong",
      "name_ja": "ハイフォン",
      "lat": 20.8449,
      "lon": 106.6881,
      "temperature": 25.6,
      "apparent_temperature": 31.0,
      "humidity": 95,
      "wind_speed": 8.5,
      "weather_code": 2,
      "is_day": 0,
      "local_time": "2026-05-07T03:45"
    },
    {
      "name": "Can Tho",
      "name_ja": "カントー",
      "lat": 10.0452,
      "lon": 105.7469,
      "temperature": 26.2,
      "apparent_temperature": 32.5,
      "humidity": 94,
      "wind_speed": 4.3,
      "weather_code": 3,
      "is_day": 0,
      "local_time": "2026-05-07T03:45"
    },
    {
      "name": "Nha Trang",
      "name_ja": "ニャチャン",
      "lat": 12.2388,
      "lon": 109.1968,
      "temperature": 26.2,
      "apparent_temperature": 31.6,
      "humidity": 92,
      "wind_speed": 8.0,
      "weather_code": 1,
      "is_day": 0,
      "local_time": "2026-05-07T03:45"
    },
    {
      "name": "Da Lat",
      "name_ja": "ダラット",
      "lat": 11.9404,
      "lon": 108.4583,
      "temperature": 16.6,
      "apparent_temperature": 17.9,
      "humidity": 99,
      "wind_speed": 7.0,
      "weather_code": 3,
      "is_day": 0,
      "local_time": "2026-05-07T03:45"
    }
  ]
}
